tamil/PowerFullInterpreter.py
tamil/__init__.py
tamil/__main__.py
tamil_lang-1.0.1.dist-info/licenses/LICENSE
tamil_lang-1.0.1.dist-info/METADATA
tamil_lang-1.0.1.dist-info/WHEEL
tamil_lang-1.0.1.dist-info/entry_points.txt
tamil_lang-1.0.1.dist-info/top_level.txt
tamil_lang-1.0.1.dist-info/RECORD
