Metadata-Version: 2.4
Name: tamil-lang
Version: 1.0.1
Summary: Tamil PowerFull Programming Language with Embedded Python by Kamalnath.S
Author-email: "Kamalnath.S" <kamalnath9443348610@gmail.com>
Requires-Python: >=3.10
License-File: LICENSE
Dynamic: license-file
